AUTHORS.rst
HISTORY.md
pyreal/__init__.py
pyreal/benchmark/__init__.py
pyreal/benchmark/challenges/__init__.py
pyreal/benchmark/challenges/explainer_challenge.py
pyreal/benchmark/challenges/gfi/__init__.py
pyreal/benchmark/challenges/gfi/global_feature_importance_challenge.py
pyreal/benchmark/challenges/gfi/shap_feature_importance_challenge.py
pyreal/benchmark/challenges/lfc/__init__.py
pyreal/benchmark/challenges/lfc/local_feature_contribution_challenge.py
pyreal/benchmark/challenges/lfc/shap_feature_contribution_challenge.py
pyreal/benchmark/dataset.py
pyreal/benchmark/download_datasets_script.py
pyreal/benchmark/main.py
pyreal/benchmark/models/Bioresponse_logistic_regression.pkl
pyreal/benchmark/models/PhishingWebsites_logistic_regression.pkl
pyreal/benchmark/models/adult_logistic_regression.pkl
pyreal/benchmark/models/analcatdata_authorship_logistic_regression.pkl
pyreal/benchmark/models/analcatdata_dmft_logistic_regression.pkl
pyreal/benchmark/models/balance-scale_logistic_regression.pkl
pyreal/benchmark/models/banknote-authentication_logistic_regression.pkl
pyreal/benchmark/models/blood-transfusion-service-center_logistic_regression.pkl
pyreal/benchmark/models/breast-w_logistic_regression.pkl
pyreal/benchmark/models/cmc_logistic_regression.pkl
pyreal/benchmark/models/cnae-9_logistic_regression.pkl
pyreal/benchmark/models/credit-approval_logistic_regression.pkl
pyreal/benchmark/models/credit-g_logistic_regression.pkl
pyreal/benchmark/models/diabetes_logistic_regression.pkl
pyreal/benchmark/models/electricity_logistic_regression.pkl
pyreal/benchmark/models/eucalyptus_logistic_regression.pkl
pyreal/benchmark/models/first-order-theorem-proving_logistic_regression.pkl
pyreal/benchmark/models/ilpd_logistic_regression.pkl
pyreal/benchmark/models/isolet_logistic_regression.pkl
pyreal/benchmark/models/jm1_logistic_regression.pkl
pyreal/benchmark/models/kc1_logistic_regression.pkl
pyreal/benchmark/models/kc2_logistic_regression.pkl
pyreal-0.4.10.dist-info/LICENSE
pyreal-0.4.10.dist-info/METADATA
pyreal-0.4.10.dist-info/WHEEL
pyreal-0.4.10.dist-info/RECORD
