Metadata-Version: 2.1
Name: pyreal
Version: 0.4.10
Summary: Library for evaluating and deploying human readable machine learning explanations.
Home-page: https://sibyl-ml.dev/
Keywords: pyreal,Pyreal
Author: Alexandra Zytek
Author-email: zyteka@mit.edu
Maintainer: MIT Data To AI Lab
Maintainer-email: dailabmit@gmail.com
Requires-Python: >=3.9,<3.12
Classifier: Intended Audience :: Developers
Classifier: Natural Language :: English
Classifier: Programming Language :: Python :: 3
Classifier: Programming Language :: Python :: 3.9
Classifier: Programming Language :: Python :: 3.10
Classifier: Programming Language :: Python :: 3.11
Requires-Dist: faiss-cpu (>=1.7.4,<2.0.0)
Requires-Dist: lime (>=0.2.0.1,<0.3.0.0)
Requires-Dist: matplotlib (>=3.6.0,<4.0.0)
Requires-Dist: numba (>=0.57.0,<0.58.0)
Requires-Dist: numpy (>=1.24.3,<2.0.0)
Requires-Dist: openai[llm] (>=1.13.3,<2.0.0)
Requires-Dist: pandas (>=1.5,<3.0)
Requires-Dist: reverse-geocoder (>=1.5.1,<2.0.0)
Requires-Dist: scikit-learn (>=1.1.2,<2.0.0)
Requires-Dist: seaborn (>=0.13.0,<0.14.0)
Requires-Dist: shap (==0.42.1)
Project-URL: Documentation, https://sibyl-dev.github.io/pyreal
Project-URL: Repository, https://github.com/DAI-Lab/pyreal
